pado/__init__.py
pado/__main__.py
pado/_compat.py
pado/_repr.py
pado/_version.py
pado/collections.py
pado/create.py
pado/dataset.py
pado/itertools.py
pado/mock.py
pado/py.typed
pado/registry.py
pado/settings.py
pado/shutil.py
pado/transporter.py
pado/types.py
pado/annotations/__init__.py
pado/annotations/annotation.py
pado/annotations/formats.py
pado/annotations/loaders.py
pado/annotations/providers.py
pado/images/__init__.py
pado/images/ids.py
pado/images/image.py
pado/images/providers.py
pado/images/tiles.py
pado/images/utils.py
pado/io/__init__.py
pado/io/checksum.py
pado/io/files.py
pado/io/paths.py
pado/io/store.py
pado/metadata/__init__.py
pado/metadata/providers.py
pado/predictions/__init__.py
pado/predictions/providers.py
pado/predictions/proxy.py
pado/predictions/writers.py
pado-0.12.0.dist-info/LICENSE
pado-0.12.0.dist-info/METADATA
pado-0.12.0.dist-info/WHEEL
pado-0.12.0.dist-info/entry_points.txt
pado-0.12.0.dist-info/top_level.txt
pado-0.12.0.dist-info/RECORD
