Metadata-Version: 2.1
Name: pado
Version: 0.12.0
Summary: cloud-native dataset library for accessing histopathological datasets
Home-page: https://github.com/Bayer-Group/pado
Download-URL: https://github.com/Bayer-Group/pado
Author: Santiago Villalba, Andreas Poehlmann
Author-email: santiago.villalba@bayer.com, andreas.poehlmann@bayer.com
License: BSD
Classifier: Development Status :: 3 - Alpha
Classifier: Intended Audience :: Science/Research
Classifier: Programming Language :: Python
Classifier: Programming Language :: Python :: 3 :: Only
Classifier: Programming Language :: Python :: 3.7
Classifier: Programming Language :: Python :: 3.8
Classifier: Programming Language :: Python :: 3.9
Classifier: Programming Language :: Python :: 3.10
Classifier: Programming Language :: Python :: 3.11
Classifier: Topic :: Scientific/Engineering
Classifier: Topic :: Scientific/Engineering :: Information Analysis
Classifier: Topic :: Scientific/Engineering :: Bio-Informatics
Classifier: Topic :: Utilities
Classifier: Operating System :: Microsoft :: Windows
Classifier: Operating System :: POSIX
Classifier: Operating System :: Unix
Classifier: Operating System :: MacOS
Requires-Python: >=3.7
License-File: LICENSE
Requires-Dist: dynaconf
Requires-Dist: fsspec
Requires-Dist: geojson-pydantic
Requires-Dist: itsdangerous
Requires-Dist: numpy (>=1.21)
Requires-Dist: orjson
Requires-Dist: pandas
Requires-Dist: platformdirs
Requires-Dist: pyarrow
Requires-Dist: pydantic
Requires-Dist: shapely (>=2)
Requires-Dist: tifffile (>=2021.6.6)
Requires-Dist: tiffslide (>=1.7.0)
Requires-Dist: toml
Requires-Dist: tqdm
Requires-Dist: typing-extensions (>=4.0)
Provides-Extra: cli
Requires-Dist: rich (>=12) ; extra == 'cli'
Requires-Dist: typer ; extra == 'cli'
Provides-Extra: create
Requires-Dist: opencv-python-headless ; extra == 'create'
Provides-Extra: dev
Requires-Dist: aiohttp ; extra == 'dev'
Requires-Dist: requests ; extra == 'dev'
Requires-Dist: mypy ; extra == 'dev'
Requires-Dist: pytest (>=6) ; extra == 'dev'
Requires-Dist: pytest-cov ; extra == 'dev'
Requires-Dist: pre-commit ; extra == 'dev'
Provides-Extra: docs
Requires-Dist: sphinx ; extra == 'docs'
Requires-Dist: sphinxemoji ; extra == 'docs'
Requires-Dist: sphinx-autodoc-typehints ; extra == 'docs'
Requires-Dist: sphinx-rtd-theme ; extra == 'docs'
